simple_hierarchy/__init__.py
simple_hierarchy/hierarchal_model.py
simple_hierarchy/tree.py
simple_hierarchy/tests/__init__.py
simple_hierarchy/tests/test_heirarchal_model.py
simple_hierarchy/tests/test_tree.py
simple_hierarchy_pytorch-0.0.1.dist-info/LICENSE.txt
simple_hierarchy_pytorch-0.0.1.dist-info/METADATA
simple_hierarchy_pytorch-0.0.1.dist-info/WHEEL
simple_hierarchy_pytorch-0.0.1.dist-info/top_level.txt
simple_hierarchy_pytorch-0.0.1.dist-info/RECORD
