Metadata-Version: 2.1
Name: simple-hierarchy-pytorch
Version: 0.0.1
Summary: simple hierarchal models in pytorch
Home-page: https://github.com/rajivsarvepalli/SimpleHierarchy
Author: Rajiv Sarvepalli
Author-email: rajiv@sarvepalli.net
License: MIT
Platform: UNKNOWN
Classifier: Programming Language :: Python :: 3
Classifier: License :: OSI Approved :: MIT License
Classifier: Operating System :: OS Independent
Requires-Python: >=3.7
Requires-Dist: torch (>=1.0)
